<?xml version="1.0" encoding="utf-8"?>
<Game>
	<Information>
		<Description des="ID=0: tiles map&#xD;" />
		<Description des="ID=14: enemy Koopa Troopa&#xD;" />
		<Description des="ID=24: Coin&#xD;" />
		<Description des="ID=10: enemy Goomba&#xD;" />
		<Description des="ID=21: Super Mushroom in LuckyBox&#xD;" />
		<Description des="ID=26: Floating Bar&#xD;" />
		<Description des="ID=17: enemy Koopa Troopa Fly&#xD;" />
		<Description des="ID=16: enemy boss&#xD;" />
		<Description des="ID=33: item flag&#xD;" />
		<Description des="ID=1: where mario can stand&#xD;" />
		<Description des="" />
	</Information>
	<Quadtree mapwidth="2632" minwidth="256">
		<Node id="3331">
			<Object id="0" index="693" x="288" y="160" width="16" height="16" />
			<Object id="0" index="660" x="288" y="176" width="16" height="16" />
			<Object id="0" index="661" x="304" y="176" width="16" height="16" />
			<Object id="0" index="661" x="320" y="176" width="16" height="16" />
			<Object id="0" index="694" x="320" y="160" width="16" height="16" />
			<Object id="0" index="694" x="304" y="160" width="16" height="16" />
		</Node>
		<Node id="3332">
			<Object id="0" index="661" x="80" y="160" width="16" height="16" />
			<Object id="0" index="661" x="96" y="160" width="16" height="16" />
			<Object id="0" index="660" x="64" y="160" width="16" height="16" />
			<Object id="0" index="662" x="112" y="160" width="16" height="16" />
		</Node>
		<Node id="3333">
			<Object id="0" index="0" x="0" y="16" width="16" height="16" />
			<Object id="0" index="0" x="160" y="16" width="16" height="16" />
			<Object id="0" index="0" x="144" y="16" width="16" height="16" />
			<Object id="0" index="0" x="128" y="16" width="16" height="16" />
			<Object id="0" index="0" x="112" y="16" width="16" height="16" />
			<Object id="0" index="0" x="96" y="16" width="16" height="16" />
			<Object id="0" index="0" x="80" y="16" width="16" height="16" />
			<Object id="0" index="0" x="64" y="16" width="16" height="16" />
			<Object id="0" index="0" x="48" y="16" width="16" height="16" />
			<Object id="0" index="0" x="32" y="16" width="16" height="16" />
			<Object id="0" index="0" x="16" y="16" width="16" height="16" />
			<Object id="0" index="0" x="0" y="0" width="16" height="16" />
			<Object id="0" index="0" x="16" y="0" width="16" height="16" />
			<Object id="0" index="0" x="32" y="0" width="16" height="16" />
			<Object id="0" index="0" x="48" y="0" width="16" height="16" />
			<Object id="0" index="0" x="64" y="0" width="16" height="16" />
			<Object id="0" index="0" x="80" y="0" width="16" height="16" />
			<Object id="0" index="0" x="96" y="0" width="16" height="16" />
			<Object id="0" index="0" x="112" y="0" width="16" height="16" />
			<Object id="0" index="0" x="128" y="0" width="16" height="16" />
			<Object id="0" index="0" x="144" y="0" width="16" height="16" />
			<Object id="0" index="0" x="160" y="0" width="16" height="16" />
			<Object id="0" index="13" x="0" y="32" width="16" height="16" />
			<Object id="0" index="13" x="0" y="48" width="16" height="16" />
			<Object id="0" index="11" x="0" y="64" width="16" height="16" />
			<Object id="0" index="13" x="64" y="32" width="16" height="16" />
			<Object id="0" index="13" x="64" y="48" width="16" height="16" />
			<Object id="0" index="11" x="64" y="64" width="16" height="16" />
			<Object id="0" index="45" x="32" y="48" width="16" height="16" />
			<Object id="0" index="13" x="48" y="32" width="16" height="16" />
			<Object id="0" index="13" x="48" y="48" width="16" height="16" />
			<Object id="0" index="13" x="16" y="48" width="16" height="16" />
			<Object id="0" index="13" x="16" y="32" width="16" height="16" />
			<Object id="0" index="46" x="32" y="32" width="16" height="16" />
			<Object id="0" index="44" x="16" y="64" width="16" height="16" />
			<Object id="0" index="44" x="32" y="64" width="16" height="16" />
			<Object id="0" index="44" x="48" y="64" width="16" height="16" />
			<Object id="0" index="12" x="16" y="80" width="16" height="16" />
			<Object id="0" index="14" x="48" y="80" width="16" height="16" />
			<Object id="0" index="13" x="32" y="80" width="16" height="16" />
			<Object id="0" index="11" x="16" y="96" width="16" height="16" />
			<Object id="0" index="11" x="32" y="96" width="16" height="16" />
			<Object id="0" index="11" x="48" y="96" width="16" height="16" />
			<Object id="0" index="693" x="160" y="80" width="16" height="16" />
			<Object id="0" index="660" x="160" y="96" width="16" height="16" />
			<Object id="0" index="661" x="80" y="160" width="16" height="16" />
			<Object id="0" index="661" x="96" y="160" width="16" height="16" />
			<Object id="0" index="660" x="64" y="160" width="16" height="16" />
			<Object id="0" index="693" x="64" y="144" width="16" height="16" />
			<Object id="0" index="694" x="80" y="144" width="16" height="16" />
			<Object id="0" index="694" x="96" y="144" width="16" height="16" />
			<Object id="0" index="695" x="112" y="144" width="16" height="16" />
			<Object id="0" index="662" x="112" y="160" width="16" height="16" />
			<Object id="1" index="0" x="0" y="0" width="256" height="32" />
		</Node>
		<Node id="3334">
			<Object id="0" index="0" x="240" y="16" width="16" height="16" />
			<Object id="0" index="0" x="224" y="16" width="16" height="16" />
			<Object id="0" index="0" x="208" y="16" width="16" height="16" />
			<Object id="0" index="0" x="192" y="16" width="16" height="16" />
			<Object id="0" index="0" x="176" y="16" width="16" height="16" />
			<Object id="0" index="0" x="160" y="16" width="16" height="16" />
			<Object id="0" index="0" x="160" y="0" width="16" height="16" />
			<Object id="0" index="0" x="176" y="0" width="16" height="16" />
			<Object id="0" index="0" x="192" y="0" width="16" height="16" />
			<Object id="0" index="0" x="208" y="0" width="16" height="16" />
			<Object id="0" index="0" x="224" y="0" width="16" height="16" />
			<Object id="0" index="0" x="240" y="0" width="16" height="16" />
			<Object id="0" index="693" x="160" y="80" width="16" height="16" />
			<Object id="0" index="660" x="160" y="96" width="16" height="16" />
			<Object id="0" index="661" x="176" y="96" width="16" height="16" />
			<Object id="0" index="694" x="176" y="80" width="16" height="16" />
			<Object id="0" index="695" x="192" y="80" width="16" height="16" />
			<Object id="0" index="662" x="192" y="96" width="16" height="16" />
			<Object id="0" index="38" x="304" y="16" width="16" height="16" />
			<Object id="0" index="38" x="304" y="0" width="16" height="16" />
			<Object id="0" index="38" x="320" y="16" width="16" height="16" />
			<Object id="0" index="38" x="320" y="0" width="16" height="16" />
			<Object id="0" index="269" x="288" y="32" width="16" height="16" />
			<Object id="0" index="270" x="304" y="32" width="16" height="16" />
			<Object id="0" index="270" x="320" y="32" width="16" height="16" />
			<Object id="0" index="693" x="288" y="160" width="16" height="16" />
			<Object id="0" index="694" x="320" y="160" width="16" height="16" />
			<Object id="0" index="694" x="304" y="160" width="16" height="16" />
			<Object id="1" index="0" x="0" y="0" width="256" height="32" />
			<Object id="1" index="0" x="288" y="32" width="64" height="16" />
		</Node>
		<Node id="3341">
			<Object id="0" index="269" x="640" y="160" width="16" height="16" />
			<Object id="0" index="270" x="656" y="160" width="16" height="16" />
			<Object id="24" index="0" x="592" y="192" width="16" height="16" />
			<Object id="24" index="0" x="608" y="192" width="16" height="16" />
			<Object id="10" index="0" x="656" y="176" width="16" height="16" />
			<Object id="1" index="0" x="640" y="160" width="112" height="16" />
		</Node>
		<Node id="3342">
			<Object id="0" index="661" x="320" y="176" width="16" height="16" />
			<Object id="0" index="662" x="336" y="176" width="16" height="16" />
			<Object id="0" index="695" x="336" y="160" width="16" height="16" />
			<Object id="0" index="694" x="320" y="160" width="16" height="16" />
			<Object id="14" index="0" x="416" y="160" width="16" height="16" />
			<Object id="24" index="0" x="432" y="160" width="16" height="16" />
			<Object id="24" index="0" x="448" y="160" width="16" height="16" />
			<Object id="24" index="0" x="464" y="160" width="16" height="16" />
		</Node>
		<Node id="3343">
			<Object id="0" index="38" x="320" y="16" width="16" height="16" />
			<Object id="0" index="38" x="320" y="0" width="16" height="16" />
			<Object id="0" index="271" x="336" y="32" width="16" height="16" />
			<Object id="0" index="270" x="320" y="32" width="16" height="16" />
			<Object id="0" index="38" x="400" y="0" width="16" height="16" />
			<Object id="0" index="38" x="400" y="16" width="16" height="16" />
			<Object id="0" index="38" x="400" y="32" width="16" height="16" />
			<Object id="0" index="38" x="400" y="48" width="16" height="16" />
			<Object id="0" index="38" x="400" y="64" width="16" height="16" />
			<Object id="0" index="38" x="480" y="0" width="16" height="16" />
			<Object id="0" index="38" x="480" y="16" width="16" height="16" />
			<Object id="0" index="38" x="480" y="32" width="16" height="16" />
			<Object id="0" index="38" x="480" y="48" width="16" height="16" />
			<Object id="0" index="38" x="480" y="64" width="16" height="16" />
			<Object id="0" index="38" x="464" y="64" width="16" height="16" />
			<Object id="0" index="38" x="464" y="48" width="16" height="16" />
			<Object id="0" index="38" x="464" y="32" width="16" height="16" />
			<Object id="0" index="38" x="464" y="16" width="16" height="16" />
			<Object id="0" index="38" x="464" y="0" width="16" height="16" />
			<Object id="0" index="38" x="448" y="0" width="16" height="16" />
			<Object id="0" index="38" x="448" y="16" width="16" height="16" />
			<Object id="0" index="38" x="448" y="32" width="16" height="16" />
			<Object id="0" index="38" x="448" y="48" width="16" height="16" />
			<Object id="0" index="38" x="448" y="64" width="16" height="16" />
			<Object id="0" index="38" x="432" y="64" width="16" height="16" />
			<Object id="0" index="38" x="432" y="48" width="16" height="16" />
			<Object id="0" index="38" x="432" y="32" width="16" height="16" />
			<Object id="0" index="38" x="432" y="16" width="16" height="16" />
			<Object id="0" index="38" x="432" y="0" width="16" height="16" />
			<Object id="0" index="38" x="416" y="0" width="16" height="16" />
			<Object id="0" index="38" x="416" y="16" width="16" height="16" />
			<Object id="0" index="38" x="416" y="32" width="16" height="16" />
			<Object id="0" index="38" x="416" y="48" width="16" height="16" />
			<Object id="0" index="38" x="416" y="64" width="16" height="16" />
			<Object id="0" index="269" x="384" y="80" width="16" height="16" />
			<Object id="0" index="270" x="400" y="80" width="16" height="16" />
			<Object id="0" index="270" x="416" y="80" width="16" height="16" />
			<Object id="0" index="270" x="432" y="80" width="16" height="16" />
			<Object id="0" index="270" x="448" y="80" width="16" height="16" />
			<Object id="0" index="270" x="464" y="80" width="16" height="16" />
			<Object id="0" index="270" x="480" y="80" width="16" height="16" />
			<Object id="0" index="38" x="464" y="96" width="16" height="16" />
			<Object id="0" index="38" x="464" y="112" width="16" height="16" />
			<Object id="0" index="38" x="464" y="128" width="16" height="16" />
			<Object id="0" index="38" x="448" y="96" width="16" height="16" />
			<Object id="0" index="38" x="448" y="112" width="16" height="16" />
			<Object id="0" index="38" x="448" y="128" width="16" height="16" />
			<Object id="0" index="38" x="432" y="128" width="16" height="16" />
			<Object id="0" index="38" x="432" y="112" width="16" height="16" />
			<Object id="0" index="38" x="432" y="96" width="16" height="16" />
			<Object id="0" index="271" x="480" y="144" width="16" height="16" />
			<Object id="0" index="270" x="432" y="144" width="16" height="16" />
			<Object id="0" index="270" x="448" y="144" width="16" height="16" />
			<Object id="0" index="270" x="464" y="144" width="16" height="16" />
			<Object id="0" index="695" x="336" y="160" width="16" height="16" />
			<Object id="0" index="694" x="320" y="160" width="16" height="16" />
			<Object id="14" index="0" x="416" y="160" width="16" height="16" />
			<Object id="24" index="0" x="432" y="160" width="16" height="16" />
			<Object id="24" index="0" x="448" y="160" width="16" height="16" />
			<Object id="24" index="0" x="464" y="160" width="16" height="16" />
			<Object id="1" index="0" x="288" y="32" width="64" height="16" />
			<Object id="0" index="335" x="416" y="144" width="16" height="16" />
			<Object id="1" index="0" x="416" y="144" width="80" height="16" />
			<Object id="1" index="0" x="384" y="80" width="128" height="16" />
		</Node>
		<Node id="3344">
			<Object id="0" index="38" x="480" y="0" width="16" height="16" />
			<Object id="0" index="38" x="480" y="16" width="16" height="16" />
			<Object id="0" index="38" x="480" y="32" width="16" height="16" />
			<Object id="0" index="38" x="480" y="48" width="16" height="16" />
			<Object id="0" index="38" x="480" y="64" width="16" height="16" />
			<Object id="0" index="271" x="496" y="80" width="16" height="16" />
			<Object id="0" index="270" x="480" y="80" width="16" height="16" />
			<Object id="0" index="271" x="480" y="144" width="16" height="16" />
			<Object id="0" index="38" x="528" y="0" width="16" height="16" />
			<Object id="0" index="38" x="528" y="16" width="16" height="16" />
			<Object id="0" index="269" x="512" y="32" width="16" height="16" />
			<Object id="0" index="270" x="528" y="32" width="16" height="16" />
			<Object id="0" index="271" x="544" y="32" width="16" height="16" />
			<Object id="0" index="38" x="576" y="0" width="16" height="16" />
			<Object id="0" index="38" x="576" y="16" width="16" height="16" />
			<Object id="0" index="38" x="576" y="32" width="16" height="16" />
			<Object id="0" index="38" x="576" y="64" width="16" height="16" />
			<Object id="0" index="38" x="576" y="80" width="16" height="16" />
			<Object id="0" index="38" x="576" y="48" width="16" height="16" />
			<Object id="0" index="38" x="592" y="80" width="16" height="16" />
			<Object id="0" index="38" x="608" y="80" width="16" height="16" />
			<Object id="0" index="38" x="608" y="64" width="16" height="16" />
			<Object id="0" index="38" x="592" y="64" width="16" height="16" />
			<Object id="0" index="38" x="592" y="48" width="16" height="16" />
			<Object id="0" index="38" x="608" y="48" width="16" height="16" />
			<Object id="0" index="38" x="608" y="32" width="16" height="16" />
			<Object id="0" index="38" x="592" y="32" width="16" height="16" />
			<Object id="0" index="38" x="592" y="16" width="16" height="16" />
			<Object id="0" index="38" x="608" y="16" width="16" height="16" />
			<Object id="0" index="38" x="608" y="0" width="16" height="16" />
			<Object id="0" index="38" x="592" y="0" width="16" height="16" />
			<Object id="0" index="269" x="560" y="96" width="16" height="16" />
			<Object id="0" index="270" x="576" y="96" width="16" height="16" />
			<Object id="0" index="270" x="592" y="96" width="16" height="16" />
			<Object id="0" index="270" x="608" y="96" width="16" height="16" />
			<Object id="0" index="271" x="624" y="96" width="16" height="16" />
			<Object id="0" index="38" x="656" y="0" width="16" height="16" />
			<Object id="0" index="38" x="656" y="16" width="16" height="16" />
			<Object id="0" index="38" x="656" y="32" width="16" height="16" />
			<Object id="0" index="38" x="656" y="48" width="16" height="16" />
			<Object id="0" index="38" x="656" y="64" width="16" height="16" />
			<Object id="0" index="38" x="656" y="80" width="16" height="16" />
			<Object id="0" index="38" x="656" y="96" width="16" height="16" />
			<Object id="0" index="38" x="656" y="112" width="16" height="16" />
			<Object id="0" index="38" x="656" y="128" width="16" height="16" />
			<Object id="0" index="38" x="656" y="144" width="16" height="16" />
			<Object id="0" index="269" x="640" y="160" width="16" height="16" />
			<Object id="0" index="270" x="656" y="160" width="16" height="16" />
			<Object id="0" index="660" x="560" y="112" width="16" height="16" />
			<Object id="0" index="661" x="576" y="112" width="16" height="16" />
			<Object id="0" index="662" x="592" y="112" width="16" height="16" />
			<Object id="0" index="660" x="608" y="128" width="16" height="16" />
			<Object id="0" index="661" x="624" y="128" width="16" height="16" />
			<Object id="0" index="662" x="640" y="128" width="16" height="16" />
			<Object id="0" index="693" x="608" y="112" width="16" height="16" />
			<Object id="0" index="694" x="624" y="112" width="16" height="16" />
			<Object id="0" index="695" x="640" y="112" width="16" height="16" />
			<Object id="24" index="0" x="528" y="48" width="16" height="16" />
			<Object id="1" index="0" x="416" y="144" width="80" height="16" />
			<Object id="1" index="0" x="384" y="80" width="128" height="16" />
			<Object id="1" index="0" x="512" y="32" width="48" height="16" />
			<Object id="1" index="0" x="560" y="96" width="80" height="16" />
			<Object id="1" index="0" x="640" y="160" width="112" height="16" />
		</Node>
		<Node id="3431">
			<Object id="0" index="693" x="832" y="160" width="16" height="16" />
			<Object id="0" index="694" x="848" y="160" width="16" height="16" />
			<Object id="0" index="694" x="864" y="160" width="16" height="16" />
			<Object id="0" index="695" x="880" y="160" width="16" height="16" />
			<Object id="0" index="660" x="832" y="176" width="16" height="16" />
			<Object id="0" index="661" x="848" y="176" width="16" height="16" />
			<Object id="0" index="661" x="864" y="176" width="16" height="16" />
			<Object id="0" index="662" x="880" y="176" width="16" height="16" />
			<Object id="24" index="0" x="960" y="160" width="16" height="16" />
			<Object id="24" index="0" x="976" y="160" width="16" height="16" />
		</Node>
		<Node id="3432">
			<Object id="0" index="270" x="656" y="160" width="16" height="16" />
			<Object id="0" index="270" x="672" y="160" width="16" height="16" />
			<Object id="0" index="270" x="688" y="160" width="16" height="16" />
			<Object id="0" index="270" x="704" y="160" width="16" height="16" />
			<Object id="0" index="270" x="720" y="160" width="16" height="16" />
			<Object id="0" index="271" x="736" y="160" width="16" height="16" />
			<Object id="10" index="0" x="656" y="176" width="16" height="16" />
			<Object id="10" index="0" x="704" y="176" width="16" height="16" />
			<Object id="1" index="0" x="640" y="160" width="112" height="16" />
		</Node>
		<Node id="3433">
			<Object id="0" index="38" x="656" y="0" width="16" height="16" />
			<Object id="0" index="38" x="656" y="16" width="16" height="16" />
			<Object id="0" index="38" x="656" y="32" width="16" height="16" />
			<Object id="0" index="38" x="656" y="48" width="16" height="16" />
			<Object id="0" index="38" x="656" y="64" width="16" height="16" />
			<Object id="0" index="38" x="656" y="80" width="16" height="16" />
			<Object id="0" index="38" x="656" y="96" width="16" height="16" />
			<Object id="0" index="38" x="656" y="112" width="16" height="16" />
			<Object id="0" index="38" x="656" y="128" width="16" height="16" />
			<Object id="0" index="38" x="656" y="144" width="16" height="16" />
			<Object id="0" index="38" x="672" y="0" width="16" height="16" />
			<Object id="0" index="38" x="688" y="0" width="16" height="16" />
			<Object id="0" index="38" x="704" y="0" width="16" height="16" />
			<Object id="0" index="38" x="720" y="0" width="16" height="16" />
			<Object id="0" index="38" x="720" y="16" width="16" height="16" />
			<Object id="0" index="38" x="704" y="16" width="16" height="16" />
			<Object id="0" index="38" x="688" y="16" width="16" height="16" />
			<Object id="0" index="38" x="672" y="16" width="16" height="16" />
			<Object id="0" index="38" x="672" y="32" width="16" height="16" />
			<Object id="0" index="38" x="688" y="32" width="16" height="16" />
			<Object id="0" index="38" x="704" y="32" width="16" height="16" />
			<Object id="0" index="38" x="720" y="32" width="16" height="16" />
			<Object id="0" index="38" x="720" y="48" width="16" height="16" />
			<Object id="0" index="38" x="704" y="48" width="16" height="16" />
			<Object id="0" index="38" x="688" y="48" width="16" height="16" />
			<Object id="0" index="38" x="672" y="48" width="16" height="16" />
			<Object id="0" index="38" x="672" y="64" width="16" height="16" />
			<Object id="0" index="38" x="688" y="64" width="16" height="16" />
			<Object id="0" index="38" x="704" y="64" width="16" height="16" />
			<Object id="0" index="38" x="720" y="64" width="16" height="16" />
			<Object id="0" index="38" x="720" y="80" width="16" height="16" />
			<Object id="0" index="38" x="704" y="80" width="16" height="16" />
			<Object id="0" index="38" x="688" y="80" width="16" height="16" />
			<Object id="0" index="38" x="672" y="80" width="16" height="16" />
			<Object id="0" index="38" x="672" y="96" width="16" height="16" />
			<Object id="0" index="38" x="688" y="96" width="16" height="16" />
			<Object id="0" index="38" x="704" y="96" width="16" height="16" />
			<Object id="0" index="38" x="720" y="96" width="16" height="16" />
			<Object id="0" index="38" x="720" y="112" width="16" height="16" />
			<Object id="0" index="38" x="704" y="112" width="16" height="16" />
			<Object id="0" index="38" x="688" y="112" width="16" height="16" />
			<Object id="0" index="38" x="672" y="112" width="16" height="16" />
			<Object id="0" index="38" x="672" y="128" width="16" height="16" />
			<Object id="0" index="38" x="688" y="128" width="16" height="16" />
			<Object id="0" index="38" x="704" y="128" width="16" height="16" />
			<Object id="0" index="38" x="720" y="128" width="16" height="16" />
			<Object id="0" index="38" x="720" y="144" width="16" height="16" />
			<Object id="0" index="38" x="704" y="144" width="16" height="16" />
			<Object id="0" index="38" x="688" y="144" width="16" height="16" />
			<Object id="0" index="38" x="672" y="144" width="16" height="16" />
			<Object id="0" index="270" x="656" y="160" width="16" height="16" />
			<Object id="0" index="270" x="672" y="160" width="16" height="16" />
			<Object id="0" index="270" x="688" y="160" width="16" height="16" />
			<Object id="0" index="270" x="704" y="160" width="16" height="16" />
			<Object id="0" index="270" x="720" y="160" width="16" height="16" />
			<Object id="0" index="271" x="736" y="160" width="16" height="16" />
			<Object id="0" index="38" x="816" y="0" width="16" height="16" />
			<Object id="0" index="269" x="800" y="16" width="16" height="16" />
			<Object id="0" index="270" x="816" y="16" width="16" height="16" />
			<Object id="0" index="693" x="752" y="32" width="16" height="16" />
			<Object id="0" index="660" x="752" y="48" width="16" height="16" />
			<Object id="0" index="661" x="768" y="48" width="16" height="16" />
			<Object id="0" index="694" x="768" y="32" width="16" height="16" />
			<Object id="0" index="695" x="784" y="32" width="16" height="16" />
			<Object id="0" index="662" x="784" y="48" width="16" height="16" />
			<Object id="24" index="0" x="800" y="128" width="16" height="16" />
			<Object id="24" index="0" x="816" y="128" width="16" height="16" />
			<Object id="1" index="0" x="640" y="160" width="112" height="16" />
			<Object id="1" index="0" x="800" y="16" width="64" height="16" />
		</Node>
		<Node id="3434">
			<Object id="0" index="38" x="816" y="0" width="16" height="16" />
			<Object id="0" index="38" x="832" y="0" width="16" height="16" />
			<Object id="0" index="271" x="848" y="16" width="16" height="16" />
			<Object id="0" index="270" x="816" y="16" width="16" height="16" />
			<Object id="0" index="270" x="832" y="16" width="16" height="16" />
			<Object id="0" index="38" x="960" y="0" width="16" height="16" />
			<Object id="0" index="38" x="976" y="0" width="16" height="16" />
			<Object id="0" index="269" x="944" y="16" width="16" height="16" />
			<Object id="0" index="270" x="960" y="16" width="16" height="16" />
			<Object id="0" index="270" x="976" y="16" width="16" height="16" />
			<Object id="0" index="38" x="976" y="32" width="16" height="16" />
			<Object id="0" index="38" x="976" y="48" width="16" height="16" />
			<Object id="0" index="38" x="976" y="128" width="16" height="16" />
			<Object id="0" index="38" x="976" y="112" width="16" height="16" />
			<Object id="0" index="38" x="976" y="96" width="16" height="16" />
			<Object id="0" index="38" x="976" y="80" width="16" height="16" />
			<Object id="0" index="38" x="976" y="64" width="16" height="16" />
			<Object id="0" index="269" x="960" y="144" width="16" height="16" />
			<Object id="0" index="270" x="976" y="144" width="16" height="16" />
			<Object id="0" index="693" x="832" y="160" width="16" height="16" />
			<Object id="0" index="694" x="848" y="160" width="16" height="16" />
			<Object id="0" index="694" x="864" y="160" width="16" height="16" />
			<Object id="0" index="695" x="880" y="160" width="16" height="16" />
			<Object id="0" index="693" x="928" y="80" width="16" height="16" />
			<Object id="0" index="660" x="928" y="96" width="16" height="16" />
			<Object id="0" index="661" x="944" y="96" width="16" height="16" />
			<Object id="0" index="662" x="960" y="96" width="16" height="16" />
			<Object id="0" index="694" x="944" y="80" width="16" height="16" />
			<Object id="0" index="695" x="960" y="80" width="16" height="16" />
			<Object id="24" index="0" x="816" y="128" width="16" height="16" />
			<Object id="21" index="0" x="944" y="64" width="16" height="16" />
			<Object id="24" index="0" x="960" y="160" width="16" height="16" />
			<Object id="24" index="0" x="976" y="160" width="16" height="16" />
			<Object id="26" index="0" x="864" y="64" width="16" height="16" />
			<Object id="1" index="0" x="800" y="16" width="64" height="16" />
			<Object id="1" index="0" x="960" y="144" width="64" height="16" />
			<Object id="1" index="0" x="944" y="16" width="80" height="16" />
		</Node>
		<Node id="3441">
			<Object id="17" index="0" x="1184" y="160" width="16" height="16" />
		</Node>
		<Node id="3442">
			<Object id="24" index="0" x="976" y="160" width="16" height="16" />
			<Object id="24" index="0" x="992" y="160" width="16" height="16" />
			<Object id="24" index="0" x="1008" y="160" width="16" height="16" />
		</Node>
		<Node id="3443">
			<Object id="0" index="38" x="976" y="0" width="16" height="16" />
			<Object id="0" index="38" x="992" y="0" width="16" height="16" />
			<Object id="0" index="270" x="976" y="16" width="16" height="16" />
			<Object id="0" index="270" x="992" y="16" width="16" height="16" />
			<Object id="0" index="271" x="1008" y="16" width="16" height="16" />
			<Object id="0" index="38" x="992" y="32" width="16" height="16" />
			<Object id="0" index="38" x="976" y="32" width="16" height="16" />
			<Object id="0" index="38" x="976" y="48" width="16" height="16" />
			<Object id="0" index="38" x="992" y="48" width="16" height="16" />
			<Object id="0" index="38" x="992" y="64" width="16" height="16" />
			<Object id="0" index="38" x="992" y="80" width="16" height="16" />
			<Object id="0" index="38" x="992" y="96" width="16" height="16" />
			<Object id="0" index="38" x="992" y="112" width="16" height="16" />
			<Object id="0" index="38" x="992" y="128" width="16" height="16" />
			<Object id="0" index="38" x="976" y="128" width="16" height="16" />
			<Object id="0" index="38" x="976" y="112" width="16" height="16" />
			<Object id="0" index="38" x="976" y="96" width="16" height="16" />
			<Object id="0" index="38" x="976" y="80" width="16" height="16" />
			<Object id="0" index="38" x="976" y="64" width="16" height="16" />
			<Object id="0" index="270" x="976" y="144" width="16" height="16" />
			<Object id="0" index="270" x="992" y="144" width="16" height="16" />
			<Object id="0" index="271" x="1008" y="144" width="16" height="16" />
			<Object id="0" index="38" x="1056" y="0" width="16" height="16" />
			<Object id="0" index="38" x="1072" y="0" width="16" height="16" />
			<Object id="0" index="38" x="1088" y="0" width="16" height="16" />
			<Object id="0" index="269" x="1040" y="16" width="16" height="16" />
			<Object id="0" index="270" x="1056" y="16" width="16" height="16" />
			<Object id="0" index="270" x="1072" y="16" width="16" height="16" />
			<Object id="0" index="270" x="1088" y="16" width="16" height="16" />
			<Object id="0" index="271" x="1104" y="16" width="16" height="16" />
			<Object id="0" index="38" x="1136" y="0" width="16" height="16" />
			<Object id="0" index="38" x="1136" y="16" width="16" height="16" />
			<Object id="0" index="38" x="1136" y="32" width="16" height="16" />
			<Object id="0" index="38" x="1136" y="48" width="16" height="16" />
			<Object id="0" index="38" x="1136" y="64" width="16" height="16" />
			<Object id="0" index="269" x="1120" y="80" width="16" height="16" />
			<Object id="0" index="270" x="1136" y="80" width="16" height="16" />
			<Object id="24" index="0" x="976" y="160" width="16" height="16" />
			<Object id="24" index="0" x="992" y="160" width="16" height="16" />
			<Object id="24" index="0" x="1008" y="160" width="16" height="16" />
			<Object id="1" index="0" x="960" y="144" width="64" height="16" />
			<Object id="1" index="0" x="944" y="16" width="80" height="16" />
			<Object id="1" index="0" x="1040" y="16" width="80" height="16" />
			<Object id="1" index="0" x="1120" y="80" width="48" height="16" />
		</Node>
		<Node id="3444">
			<Object id="0" index="38" x="1136" y="0" width="16" height="16" />
			<Object id="0" index="38" x="1136" y="16" width="16" height="16" />
			<Object id="0" index="38" x="1136" y="32" width="16" height="16" />
			<Object id="0" index="38" x="1136" y="48" width="16" height="16" />
			<Object id="0" index="38" x="1136" y="64" width="16" height="16" />
			<Object id="0" index="270" x="1136" y="80" width="16" height="16" />
			<Object id="0" index="271" x="1152" y="80" width="16" height="16" />
			<Object id="0" index="38" x="1232" y="0" width="16" height="16" />
			<Object id="0" index="38" x="1232" y="16" width="16" height="16" />
			<Object id="0" index="38" x="1232" y="32" width="16" height="16" />
			<Object id="0" index="38" x="1232" y="48" width="16" height="16" />
			<Object id="0" index="38" x="1232" y="64" width="16" height="16" />
			<Object id="0" index="38" x="1232" y="80" width="16" height="16" />
			<Object id="0" index="38" x="1232" y="96" width="16" height="16" />
			<Object id="0" index="38" x="1232" y="112" width="16" height="16" />
			<Object id="0" index="38" x="1248" y="0" width="16" height="16" />
			<Object id="0" index="38" x="1264" y="0" width="16" height="16" />
			<Object id="0" index="38" x="1280" y="0" width="16" height="16" />
			<Object id="0" index="38" x="1280" y="16" width="16" height="16" />
			<Object id="0" index="38" x="1264" y="16" width="16" height="16" />
			<Object id="0" index="38" x="1248" y="16" width="16" height="16" />
			<Object id="0" index="38" x="1248" y="32" width="16" height="16" />
			<Object id="0" index="38" x="1264" y="32" width="16" height="16" />
			<Object id="0" index="38" x="1280" y="32" width="16" height="16" />
			<Object id="0" index="38" x="1280" y="48" width="16" height="16" />
			<Object id="0" index="38" x="1264" y="48" width="16" height="16" />
			<Object id="0" index="38" x="1248" y="48" width="16" height="16" />
			<Object id="0" index="38" x="1248" y="64" width="16" height="16" />
			<Object id="0" index="38" x="1264" y="64" width="16" height="16" />
			<Object id="0" index="38" x="1280" y="64" width="16" height="16" />
			<Object id="0" index="38" x="1280" y="80" width="16" height="16" />
			<Object id="0" index="38" x="1264" y="80" width="16" height="16" />
			<Object id="0" index="38" x="1248" y="80" width="16" height="16" />
			<Object id="0" index="38" x="1248" y="96" width="16" height="16" />
			<Object id="0" index="38" x="1264" y="96" width="16" height="16" />
			<Object id="0" index="38" x="1280" y="96" width="16" height="16" />
			<Object id="0" index="38" x="1280" y="112" width="16" height="16" />
			<Object id="0" index="38" x="1264" y="112" width="16" height="16" />
			<Object id="0" index="38" x="1248" y="112" width="16" height="16" />
			<Object id="0" index="269" x="1216" y="128" width="16" height="16" />
			<Object id="0" index="270" x="1232" y="128" width="16" height="16" />
			<Object id="0" index="270" x="1248" y="128" width="16" height="16" />
			<Object id="0" index="270" x="1264" y="128" width="16" height="16" />
			<Object id="0" index="270" x="1280" y="128" width="16" height="16" />
			<Object id="0" index="271" x="1296" y="128" width="16" height="16" />
			<Object id="17" index="0" x="1184" y="160" width="16" height="16" />
			<Object id="10" index="0" x="1248" y="144" width="16" height="16" />
			<Object id="1" index="0" x="1216" y="128" width="96" height="16" />
			<Object id="1" index="0" x="1120" y="80" width="48" height="16" />
		</Node>
		<Node id="4331">
			<Object id="0" index="661" x="1616" y="176" width="16" height="16" />
			<Object id="0" index="661" x="1632" y="176" width="16" height="16" />
			<Object id="0" index="660" x="1600" y="176" width="16" height="16" />
			<Object id="0" index="693" x="1600" y="160" width="16" height="16" />
			<Object id="0" index="694" x="1616" y="160" width="16" height="16" />
			<Object id="0" index="694" x="1632" y="160" width="16" height="16" />
			<Object id="24" index="0" x="1472" y="160" width="16" height="16" />
			<Object id="24" index="0" x="1488" y="160" width="16" height="16" />
			<Object id="24" index="0" x="1552" y="160" width="16" height="16" />
			<Object id="24" index="0" x="1568" y="160" width="16" height="16" />
		</Node>
		<Node id="4332">
			<Object id="24" index="0" x="1472" y="160" width="16" height="16" />
		</Node>
		<Node id="4333">
			<Object id="0" index="693" x="1344" y="112" width="16" height="16" />
			<Object id="0" index="660" x="1344" y="128" width="16" height="16" />
			<Object id="0" index="661" x="1360" y="128" width="16" height="16" />
			<Object id="0" index="662" x="1376" y="128" width="16" height="16" />
			<Object id="0" index="695" x="1376" y="112" width="16" height="16" />
			<Object id="0" index="694" x="1360" y="112" width="16" height="16" />
			<Object id="0" index="693" x="1424" y="128" width="16" height="16" />
			<Object id="0" index="660" x="1424" y="144" width="16" height="16" />
			<Object id="0" index="661" x="1440" y="144" width="16" height="16" />
			<Object id="0" index="694" x="1440" y="128" width="16" height="16" />
			<Object id="0" index="695" x="1456" y="128" width="16" height="16" />
			<Object id="0" index="662" x="1456" y="144" width="16" height="16" />
			<Object id="26" index="0" x="1328" y="96" width="16" height="16" />
			<Object id="26" index="0" x="1456" y="80" width="16" height="16" />
			<Object id="24" index="0" x="1344" y="144" width="16" height="16" />
			<Object id="24" index="0" x="1360" y="144" width="16" height="16" />
			<Object id="24" index="0" x="1472" y="160" width="16" height="16" />
		</Node>
		<Node id="4334">
			<Object id="0" index="38" x="1584" y="0" width="16" height="16" />
			<Object id="0" index="38" x="1584" y="16" width="16" height="16" />
			<Object id="0" index="38" x="1584" y="32" width="16" height="16" />
			<Object id="0" index="38" x="1600" y="32" width="16" height="16" />
			<Object id="0" index="38" x="1600" y="16" width="16" height="16" />
			<Object id="0" index="38" x="1600" y="0" width="16" height="16" />
			<Object id="0" index="269" x="1568" y="48" width="16" height="16" />
			<Object id="0" index="270" x="1584" y="48" width="16" height="16" />
			<Object id="0" index="270" x="1600" y="48" width="16" height="16" />
			<Object id="0" index="271" x="1616" y="48" width="16" height="16" />
			<Object id="0" index="693" x="1504" y="32" width="16" height="16" />
			<Object id="0" index="660" x="1504" y="48" width="16" height="16" />
			<Object id="0" index="661" x="1520" y="48" width="16" height="16" />
			<Object id="0" index="694" x="1520" y="32" width="16" height="16" />
			<Object id="0" index="695" x="1536" y="32" width="16" height="16" />
			<Object id="0" index="662" x="1536" y="48" width="16" height="16" />
			<Object id="0" index="693" x="1600" y="160" width="16" height="16" />
			<Object id="0" index="694" x="1616" y="160" width="16" height="16" />
			<Object id="0" index="694" x="1632" y="160" width="16" height="16" />
			<Object id="24" index="0" x="1472" y="160" width="16" height="16" />
			<Object id="24" index="0" x="1488" y="160" width="16" height="16" />
			<Object id="24" index="0" x="1552" y="160" width="16" height="16" />
			<Object id="24" index="0" x="1568" y="160" width="16" height="16" />
			<Object id="1" index="0" x="1568" y="48" width="64" height="16" />
		</Node>
		<Node id="4341">
			<Object id="0" index="661" x="1856" y="176" width="16" height="16" />
			<Object id="0" index="661" x="1872" y="176" width="16" height="16" />
			<Object id="0" index="660" x="1840" y="176" width="16" height="16" />
			<Object id="0" index="693" x="1840" y="160" width="16" height="16" />
			<Object id="0" index="694" x="1856" y="160" width="16" height="16" />
			<Object id="0" index="694" x="1872" y="160" width="16" height="16" />
			<Object id="0" index="695" x="1888" y="160" width="16" height="16" />
			<Object id="0" index="662" x="1888" y="176" width="16" height="16" />
			<Object id="17" index="0" x="1824" y="160" width="16" height="16" />
		</Node>
		<Node id="4342">
			<Object id="0" index="661" x="1632" y="176" width="16" height="16" />
			<Object id="0" index="662" x="1648" y="176" width="16" height="16" />
			<Object id="0" index="694" x="1632" y="160" width="16" height="16" />
			<Object id="0" index="695" x="1648" y="160" width="16" height="16" />
		</Node>
		<Node id="4343">
			<Object id="0" index="38" x="1680" y="16" width="16" height="16" />
			<Object id="0" index="38" x="1680" y="0" width="16" height="16" />
			<Object id="0" index="38" x="1680" y="32" width="16" height="16" />
			<Object id="0" index="38" x="1680" y="48" width="16" height="16" />
			<Object id="0" index="38" x="1680" y="64" width="16" height="16" />
			<Object id="0" index="38" x="1680" y="80" width="16" height="16" />
			<Object id="0" index="38" x="1680" y="96" width="16" height="16" />
			<Object id="0" index="38" x="1760" y="0" width="16" height="16" />
			<Object id="0" index="38" x="1760" y="16" width="16" height="16" />
			<Object id="0" index="38" x="1760" y="32" width="16" height="16" />
			<Object id="0" index="38" x="1760" y="48" width="16" height="16" />
			<Object id="0" index="38" x="1760" y="64" width="16" height="16" />
			<Object id="0" index="38" x="1760" y="80" width="16" height="16" />
			<Object id="0" index="38" x="1760" y="96" width="16" height="16" />
			<Object id="0" index="38" x="1744" y="96" width="16" height="16" />
			<Object id="0" index="38" x="1744" y="80" width="16" height="16" />
			<Object id="0" index="38" x="1744" y="64" width="16" height="16" />
			<Object id="0" index="38" x="1744" y="48" width="16" height="16" />
			<Object id="0" index="38" x="1744" y="32" width="16" height="16" />
			<Object id="0" index="38" x="1744" y="16" width="16" height="16" />
			<Object id="0" index="38" x="1744" y="0" width="16" height="16" />
			<Object id="0" index="38" x="1728" y="0" width="16" height="16" />
			<Object id="0" index="38" x="1728" y="16" width="16" height="16" />
			<Object id="0" index="38" x="1728" y="32" width="16" height="16" />
			<Object id="0" index="38" x="1728" y="48" width="16" height="16" />
			<Object id="0" index="38" x="1728" y="64" width="16" height="16" />
			<Object id="0" index="38" x="1728" y="80" width="16" height="16" />
			<Object id="0" index="38" x="1728" y="96" width="16" height="16" />
			<Object id="0" index="38" x="1712" y="96" width="16" height="16" />
			<Object id="0" index="38" x="1712" y="80" width="16" height="16" />
			<Object id="0" index="38" x="1712" y="64" width="16" height="16" />
			<Object id="0" index="38" x="1712" y="48" width="16" height="16" />
			<Object id="0" index="38" x="1712" y="32" width="16" height="16" />
			<Object id="0" index="38" x="1712" y="16" width="16" height="16" />
			<Object id="0" index="38" x="1712" y="0" width="16" height="16" />
			<Object id="0" index="38" x="1696" y="0" width="16" height="16" />
			<Object id="0" index="38" x="1696" y="16" width="16" height="16" />
			<Object id="0" index="38" x="1696" y="32" width="16" height="16" />
			<Object id="0" index="38" x="1696" y="48" width="16" height="16" />
			<Object id="0" index="38" x="1696" y="64" width="16" height="16" />
			<Object id="0" index="38" x="1696" y="80" width="16" height="16" />
			<Object id="0" index="38" x="1696" y="96" width="16" height="16" />
			<Object id="0" index="271" x="1776" y="112" width="16" height="16" />
			<Object id="0" index="270" x="1680" y="112" width="16" height="16" />
			<Object id="0" index="270" x="1696" y="112" width="16" height="16" />
			<Object id="0" index="270" x="1712" y="112" width="16" height="16" />
			<Object id="0" index="270" x="1728" y="112" width="16" height="16" />
			<Object id="0" index="270" x="1744" y="112" width="16" height="16" />
			<Object id="0" index="270" x="1760" y="112" width="16" height="16" />
			<Object id="0" index="694" x="1632" y="160" width="16" height="16" />
			<Object id="0" index="695" x="1648" y="160" width="16" height="16" />
			<Object id="0" index="269" x="1808" y="16" width="16" height="16" />
			<Object id="14" index="0" x="1680" y="128" width="16" height="16" />
			<Object id="24" index="0" x="1808" y="32" width="16" height="16" />
			<Object id="0" index="335" x="1664" y="112" width="16" height="16" />
			<Object id="1" index="0" x="1664" y="112" width="126" height="16" />
			<Object id="1" index="0" x="1808" y="16" width="48" height="16" />
		</Node>
		<Node id="4344">
			<Object id="0" index="38" x="1824" y="0" width="16" height="16" />
			<Object id="0" index="269" x="1808" y="16" width="16" height="16" />
			<Object id="0" index="270" x="1824" y="16" width="16" height="16" />
			<Object id="0" index="271" x="1840" y="16" width="16" height="16" />
			<Object id="0" index="38" x="1872" y="0" width="16" height="16" />
			<Object id="0" index="38" x="1872" y="16" width="16" height="16" />
			<Object id="0" index="38" x="1872" y="32" width="16" height="16" />
			<Object id="0" index="38" x="1872" y="48" width="16" height="16" />
			<Object id="0" index="38" x="1872" y="64" width="16" height="16" />
			<Object id="0" index="38" x="1888" y="0" width="16" height="16" />
			<Object id="0" index="38" x="1888" y="16" width="16" height="16" />
			<Object id="0" index="38" x="1888" y="32" width="16" height="16" />
			<Object id="0" index="38" x="1888" y="48" width="16" height="16" />
			<Object id="0" index="38" x="1888" y="64" width="16" height="16" />
			<Object id="0" index="269" x="1856" y="80" width="16" height="16" />
			<Object id="0" index="270" x="1872" y="80" width="16" height="16" />
			<Object id="0" index="270" x="1888" y="80" width="16" height="16" />
			<Object id="0" index="271" x="1904" y="80" width="16" height="16" />
			<Object id="0" index="38" x="1968" y="0" width="16" height="16" />
			<Object id="0" index="38" x="1968" y="16" width="16" height="16" />
			<Object id="0" index="38" x="1968" y="32" width="16" height="16" />
			<Object id="0" index="38" x="1968" y="48" width="16" height="16" />
			<Object id="0" index="38" x="1968" y="64" width="16" height="16" />
			<Object id="0" index="269" x="1952" y="80" width="16" height="16" />
			<Object id="0" index="270" x="1968" y="80" width="16" height="16" />
			<Object id="0" index="693" x="1840" y="160" width="16" height="16" />
			<Object id="0" index="694" x="1856" y="160" width="16" height="16" />
			<Object id="0" index="694" x="1872" y="160" width="16" height="16" />
			<Object id="0" index="695" x="1888" y="160" width="16" height="16" />
			<Object id="17" index="0" x="1824" y="160" width="16" height="16" />
			<Object id="24" index="0" x="1808" y="32" width="16" height="16" />
			<Object id="24" index="0" x="1840" y="32" width="16" height="16" />
			<Object id="24" index="0" x="1824" y="32" width="16" height="16" />
			<Object id="24" index="0" x="1920" y="144" width="16" height="16" />
			<Object id="24" index="0" x="1936" y="144" width="16" height="16" />
			<Object id="1" index="0" x="1856" y="80" width="64" height="16" />
			<Object id="1" index="0" x="1952" y="80" width="64" height="16" />
			<Object id="1" index="0" x="1808" y="16" width="48" height="16" />
		</Node>
		<Node id="4433">
			<Object id="0" index="38" x="1968" y="0" width="16" height="16" />
			<Object id="0" index="38" x="1968" y="16" width="16" height="16" />
			<Object id="0" index="38" x="1968" y="32" width="16" height="16" />
			<Object id="0" index="38" x="1968" y="48" width="16" height="16" />
			<Object id="0" index="38" x="1968" y="64" width="16" height="16" />
			<Object id="0" index="38" x="1984" y="64" width="16" height="16" />
			<Object id="0" index="38" x="1984" y="48" width="16" height="16" />
			<Object id="0" index="38" x="1984" y="32" width="16" height="16" />
			<Object id="0" index="38" x="1984" y="16" width="16" height="16" />
			<Object id="0" index="38" x="1984" y="0" width="16" height="16" />
			<Object id="0" index="270" x="1968" y="80" width="16" height="16" />
			<Object id="0" index="270" x="1984" y="80" width="16" height="16" />
			<Object id="0" index="271" x="2000" y="80" width="16" height="16" />
			<Object id="0" index="661" x="2000" y="48" width="16" height="16" />
			<Object id="0" index="662" x="2016" y="48" width="16" height="16" />
			<Object id="0" index="695" x="2016" y="32" width="16" height="16" />
			<Object id="0" index="694" x="2000" y="32" width="16" height="16" />
			<Object id="0" index="0" x="2064" y="0" width="16" height="16" />
			<Object id="0" index="0" x="2064" y="16" width="16" height="16" />
			<Object id="0" index="0" x="2080" y="16" width="16" height="16" />
			<Object id="0" index="0" x="2080" y="0" width="16" height="16" />
			<Object id="0" index="0" x="2096" y="16" width="16" height="16" />
			<Object id="0" index="0" x="2096" y="0" width="16" height="16" />
			<Object id="0" index="0" x="2128" y="0" width="16" height="16" />
			<Object id="0" index="0" x="2112" y="0" width="16" height="16" />
			<Object id="0" index="0" x="2112" y="16" width="16" height="16" />
			<Object id="0" index="0" x="2128" y="16" width="16" height="16" />
			<Object id="0" index="660" x="2096" y="96" width="16" height="16" />
			<Object id="0" index="693" x="2096" y="80" width="16" height="16" />
			<Object id="0" index="661" x="2112" y="96" width="16" height="16" />
			<Object id="0" index="694" x="2112" y="80" width="16" height="16" />
			<Object id="0" index="695" x="2128" y="80" width="16" height="16" />
			<Object id="0" index="662" x="2128" y="96" width="16" height="16" />
			<Object id="1" index="0" x="1952" y="80" width="64" height="16" />
			<Object id="1" index="0" x="2064" y="-32" width="568" height="64" />
		</Node>
		<Node id="4434">
			<Object id="0" index="0" x="2272" y="0" width="16" height="16" />
			<Object id="0" index="0" x="2256" y="0" width="16" height="16" />
			<Object id="0" index="0" x="2288" y="0" width="16" height="16" />
			<Object id="0" index="0" x="2240" y="0" width="16" height="16" />
			<Object id="0" index="0" x="2224" y="0" width="16" height="16" />
			<Object id="0" index="0" x="2208" y="0" width="16" height="16" />
			<Object id="0" index="0" x="2192" y="0" width="16" height="16" />
			<Object id="0" index="0" x="2176" y="0" width="16" height="16" />
			<Object id="0" index="0" x="2160" y="0" width="16" height="16" />
			<Object id="0" index="0" x="2144" y="0" width="16" height="16" />
			<Object id="0" index="0" x="2128" y="0" width="16" height="16" />
			<Object id="0" index="0" x="2128" y="16" width="16" height="16" />
			<Object id="0" index="0" x="2144" y="16" width="16" height="16" />
			<Object id="0" index="0" x="2160" y="16" width="16" height="16" />
			<Object id="0" index="0" x="2176" y="16" width="16" height="16" />
			<Object id="0" index="0" x="2192" y="16" width="16" height="16" />
			<Object id="0" index="0" x="2208" y="16" width="16" height="16" />
			<Object id="0" index="0" x="2224" y="16" width="16" height="16" />
			<Object id="0" index="0" x="2240" y="16" width="16" height="16" />
			<Object id="0" index="0" x="2256" y="16" width="16" height="16" />
			<Object id="0" index="0" x="2272" y="16" width="16" height="16" />
			<Object id="0" index="0" x="2288" y="16" width="16" height="16" />
			<Object id="0" index="33" x="2208" y="32" width="16" height="16" />
			<Object id="0" index="33" x="2208" y="48" width="16" height="16" />
			<Object id="0" index="33" x="2208" y="64" width="16" height="16" />
			<Object id="0" index="33" x="2208" y="80" width="16" height="16" />
			<Object id="0" index="33" x="2224" y="80" width="16" height="16" />
			<Object id="0" index="33" x="2224" y="64" width="16" height="16" />
			<Object id="0" index="33" x="2224" y="48" width="16" height="16" />
			<Object id="0" index="33" x="2224" y="32" width="16" height="16" />
			<Object id="0" index="33" x="2240" y="96" width="16" height="16" />
			<Object id="0" index="33" x="2240" y="112" width="16" height="16" />
			<Object id="0" index="33" x="2256" y="112" width="16" height="16" />
			<Object id="0" index="33" x="2256" y="96" width="16" height="16" />
			<Object id="0" index="33" x="2272" y="128" width="16" height="16" />
			<Object id="0" index="33" x="2288" y="128" width="16" height="16" />
			<Object id="0" index="33" x="2288" y="144" width="16" height="16" />
			<Object id="0" index="33" x="2272" y="144" width="16" height="16" />
			<Object id="0" index="33" x="2272" y="112" width="16" height="16" />
			<Object id="0" index="33" x="2288" y="112" width="16" height="16" />
			<Object id="0" index="33" x="2288" y="96" width="16" height="16" />
			<Object id="0" index="33" x="2272" y="96" width="16" height="16" />
			<Object id="0" index="33" x="2288" y="80" width="16" height="16" />
			<Object id="0" index="33" x="2272" y="80" width="16" height="16" />
			<Object id="0" index="33" x="2256" y="80" width="16" height="16" />
			<Object id="0" index="33" x="2240" y="80" width="16" height="16" />
			<Object id="0" index="33" x="2240" y="64" width="16" height="16" />
			<Object id="0" index="33" x="2256" y="64" width="16" height="16" />
			<Object id="0" index="33" x="2272" y="64" width="16" height="16" />
			<Object id="0" index="33" x="2288" y="64" width="16" height="16" />
			<Object id="0" index="33" x="2288" y="48" width="16" height="16" />
			<Object id="0" index="33" x="2288" y="32" width="16" height="16" />
			<Object id="0" index="33" x="2272" y="32" width="16" height="16" />
			<Object id="0" index="33" x="2272" y="48" width="16" height="16" />
			<Object id="0" index="33" x="2256" y="48" width="16" height="16" />
			<Object id="0" index="33" x="2256" y="32" width="16" height="16" />
			<Object id="0" index="33" x="2240" y="32" width="16" height="16" />
			<Object id="0" index="33" x="2240" y="48" width="16" height="16" />
			<Object id="0" index="695" x="2128" y="80" width="16" height="16" />
			<Object id="0" index="662" x="2128" y="96" width="16" height="16" />
			<Object id="0" index="693" x="2144" y="112" width="16" height="16" />
			<Object id="0" index="660" x="2144" y="128" width="16" height="16" />
			<Object id="0" index="661" x="2160" y="128" width="16" height="16" />
			<Object id="0" index="662" x="2176" y="128" width="16" height="16" />
			<Object id="0" index="695" x="2176" y="112" width="16" height="16" />
			<Object id="0" index="694" x="2160" y="112" width="16" height="16" />
			<Object id="16" index="0" x="2160" y="48" width="16" height="16" />
			<Object id="1" index="0" x="2208" y="32" width="32" height="64" />
			<Object id="1" index="0" x="2240" y="32" width="32" height="96" />
			<Object id="1" index="0" x="2272" y="32" width="32" height="128" />
			<Object id="1" index="0" x="2064" y="-32" width="568" height="64" />
		</Node>
		<Node id="4441">
			<Object id="0" index="11" x="2512" y="160" width="16" height="16" />
			<Object id="0" index="11" x="2576" y="160" width="16" height="16" />
			<Object id="0" index="44" x="2528" y="160" width="16" height="16" />
			<Object id="0" index="44" x="2544" y="160" width="16" height="16" />
			<Object id="0" index="44" x="2560" y="160" width="16" height="16" />
			<Object id="0" index="12" x="2528" y="176" width="16" height="16" />
			<Object id="0" index="14" x="2560" y="176" width="16" height="16" />
			<Object id="0" index="13" x="2544" y="176" width="16" height="16" />
			<Object id="0" index="11" x="2528" y="192" width="16" height="16" />
			<Object id="0" index="11" x="2544" y="192" width="16" height="16" />
			<Object id="0" index="11" x="2560" y="192" width="16" height="16" />
		</Node>
		<Node id="4442">
			<Object id="0" index="661" x="2352" y="160" width="16" height="16" />
			<Object id="0" index="661" x="2368" y="160" width="16" height="16" />
			<Object id="0" index="660" x="2336" y="160" width="16" height="16" />
			<Object id="0" index="662" x="2384" y="160" width="16" height="16" />
		</Node>
		<Node id="4443">
			<Object id="0" index="0" x="2464" y="0" width="16" height="16" />
			<Object id="0" index="0" x="2432" y="0" width="16" height="16" />
			<Object id="0" index="0" x="2448" y="0" width="16" height="16" />
			<Object id="0" index="0" x="2416" y="0" width="16" height="16" />
			<Object id="0" index="0" x="2400" y="0" width="16" height="16" />
			<Object id="0" index="0" x="2384" y="0" width="16" height="16" />
			<Object id="0" index="0" x="2368" y="0" width="16" height="16" />
			<Object id="0" index="0" x="2352" y="0" width="16" height="16" />
			<Object id="0" index="0" x="2336" y="0" width="16" height="16" />
			<Object id="0" index="0" x="2320" y="0" width="16" height="16" />
			<Object id="0" index="0" x="2304" y="0" width="16" height="16" />
			<Object id="0" index="0" x="2288" y="0" width="16" height="16" />
			<Object id="0" index="0" x="2288" y="16" width="16" height="16" />
			<Object id="0" index="0" x="2304" y="16" width="16" height="16" />
			<Object id="0" index="0" x="2320" y="16" width="16" height="16" />
			<Object id="0" index="0" x="2336" y="16" width="16" height="16" />
			<Object id="0" index="0" x="2352" y="16" width="16" height="16" />
			<Object id="0" index="0" x="2368" y="16" width="16" height="16" />
			<Object id="0" index="0" x="2384" y="16" width="16" height="16" />
			<Object id="0" index="0" x="2400" y="16" width="16" height="16" />
			<Object id="0" index="0" x="2416" y="16" width="16" height="16" />
			<Object id="0" index="0" x="2432" y="16" width="16" height="16" />
			<Object id="0" index="0" x="2448" y="16" width="16" height="16" />
			<Object id="0" index="0" x="2464" y="16" width="16" height="16" />
			<Object id="0" index="33" x="2288" y="128" width="16" height="16" />
			<Object id="0" index="33" x="2288" y="144" width="16" height="16" />
			<Object id="0" index="33" x="2288" y="112" width="16" height="16" />
			<Object id="0" index="33" x="2288" y="96" width="16" height="16" />
			<Object id="0" index="33" x="2288" y="80" width="16" height="16" />
			<Object id="0" index="33" x="2288" y="64" width="16" height="16" />
			<Object id="0" index="33" x="2288" y="48" width="16" height="16" />
			<Object id="0" index="33" x="2288" y="32" width="16" height="16" />
			<Object id="0" index="33" x="2432" y="32" width="16" height="16" />
			<Object id="0" index="661" x="2464" y="112" width="16" height="16" />
			<Object id="0" index="694" x="2464" y="96" width="16" height="16" />
			<Object id="0" index="660" x="2448" y="112" width="16" height="16" />
			<Object id="0" index="693" x="2448" y="96" width="16" height="16" />
			<Object id="0" index="661" x="2352" y="160" width="16" height="16" />
			<Object id="0" index="661" x="2368" y="160" width="16" height="16" />
			<Object id="0" index="660" x="2336" y="160" width="16" height="16" />
			<Object id="0" index="693" x="2336" y="144" width="16" height="16" />
			<Object id="0" index="694" x="2352" y="144" width="16" height="16" />
			<Object id="0" index="694" x="2368" y="144" width="16" height="16" />
			<Object id="0" index="695" x="2384" y="144" width="16" height="16" />
			<Object id="0" index="662" x="2384" y="160" width="16" height="16" />
			<Object id="0" index="662" x="2304" y="64" width="16" height="16" />
			<Object id="0" index="695" x="2304" y="48" width="16" height="16" />
			<Object id="33" index="0" x="2432" y="48" width="16" height="16" />
			<Object id="1" index="0" x="2272" y="32" width="32" height="128" />
			<Object id="1" index="0" x="2064" y="-32" width="568" height="64" />
		</Node>
		<Node id="4444">
			<Object id="0" index="0" x="2624" y="0" width="16" height="16" />
			<Object id="0" index="0" x="2608" y="0" width="16" height="16" />
			<Object id="0" index="0" x="2592" y="0" width="16" height="16" />
			<Object id="0" index="0" x="2576" y="0" width="16" height="16" />
			<Object id="0" index="0" x="2560" y="0" width="16" height="16" />
			<Object id="0" index="0" x="2544" y="0" width="16" height="16" />
			<Object id="0" index="0" x="2528" y="0" width="16" height="16" />
			<Object id="0" index="0" x="2512" y="0" width="16" height="16" />
			<Object id="0" index="0" x="2496" y="0" width="16" height="16" />
			<Object id="0" index="0" x="2480" y="0" width="16" height="16" />
			<Object id="0" index="0" x="2464" y="0" width="16" height="16" />
			<Object id="0" index="0" x="2464" y="16" width="16" height="16" />
			<Object id="0" index="0" x="2480" y="16" width="16" height="16" />
			<Object id="0" index="0" x="2496" y="16" width="16" height="16" />
			<Object id="0" index="0" x="2512" y="16" width="16" height="16" />
			<Object id="0" index="0" x="2528" y="16" width="16" height="16" />
			<Object id="0" index="0" x="2544" y="16" width="16" height="16" />
			<Object id="0" index="0" x="2560" y="16" width="16" height="16" />
			<Object id="0" index="0" x="2576" y="16" width="16" height="16" />
			<Object id="0" index="0" x="2592" y="16" width="16" height="16" />
			<Object id="0" index="0" x="2608" y="16" width="16" height="16" />
			<Object id="0" index="0" x="2624" y="16" width="16" height="16" />
			<Object id="0" index="13" x="2480" y="32" width="16" height="16" />
			<Object id="0" index="13" x="2480" y="48" width="16" height="16" />
			<Object id="0" index="13" x="2480" y="64" width="16" height="16" />
			<Object id="0" index="13" x="2480" y="80" width="16" height="16" />
			<Object id="0" index="13" x="2480" y="96" width="16" height="16" />
			<Object id="0" index="11" x="2480" y="112" width="16" height="16" />
			<Object id="0" index="11" x="2496" y="112" width="16" height="16" />
			<Object id="0" index="11" x="2624" y="112" width="16" height="16" />
			<Object id="0" index="11" x="2608" y="112" width="16" height="16" />
			<Object id="0" index="11" x="2592" y="112" width="16" height="16" />
			<Object id="0" index="13" x="2624" y="96" width="16" height="16" />
			<Object id="0" index="13" x="2624" y="80" width="16" height="16" />
			<Object id="0" index="13" x="2624" y="64" width="16" height="16" />
			<Object id="0" index="13" x="2624" y="48" width="16" height="16" />
			<Object id="0" index="13" x="2624" y="32" width="16" height="16" />
			<Object id="0" index="13" x="2608" y="32" width="16" height="16" />
			<Object id="0" index="13" x="2608" y="48" width="16" height="16" />
			<Object id="0" index="13" x="2608" y="64" width="16" height="16" />
			<Object id="0" index="13" x="2608" y="80" width="16" height="16" />
			<Object id="0" index="13" x="2608" y="96" width="16" height="16" />
			<Object id="0" index="13" x="2592" y="96" width="16" height="16" />
			<Object id="0" index="13" x="2592" y="80" width="16" height="16" />
			<Object id="0" index="13" x="2592" y="64" width="16" height="16" />
			<Object id="0" index="13" x="2592" y="48" width="16" height="16" />
			<Object id="0" index="13" x="2592" y="32" width="16" height="16" />
			<Object id="0" index="13" x="2496" y="96" width="16" height="16" />
			<Object id="0" index="13" x="2496" y="80" width="16" height="16" />
			<Object id="0" index="13" x="2496" y="64" width="16" height="16" />
			<Object id="0" index="13" x="2496" y="48" width="16" height="16" />
			<Object id="0" index="13" x="2496" y="32" width="16" height="16" />
			<Object id="0" index="45" x="2512" y="48" width="16" height="16" />
			<Object id="0" index="46" x="2512" y="32" width="16" height="16" />
			<Object id="0" index="13" x="2528" y="48" width="16" height="16" />
			<Object id="0" index="13" x="2528" y="32" width="16" height="16" />
			<Object id="0" index="45" x="2544" y="48" width="16" height="16" />
			<Object id="0" index="46" x="2544" y="32" width="16" height="16" />
			<Object id="0" index="13" x="2560" y="48" width="16" height="16" />
			<Object id="0" index="13" x="2560" y="32" width="16" height="16" />
			<Object id="0" index="45" x="2576" y="48" width="16" height="16" />
			<Object id="0" index="46" x="2576" y="32" width="16" height="16" />
			<Object id="0" index="13" x="2512" y="64" width="16" height="16" />
			<Object id="0" index="13" x="2528" y="64" width="16" height="16" />
			<Object id="0" index="13" x="2544" y="64" width="16" height="16" />
			<Object id="0" index="13" x="2560" y="64" width="16" height="16" />
			<Object id="0" index="13" x="2576" y="64" width="16" height="16" />
			<Object id="0" index="13" x="2512" y="80" width="16" height="16" />
			<Object id="0" index="13" x="2512" y="96" width="16" height="16" />
			<Object id="0" index="13" x="2576" y="80" width="16" height="16" />
			<Object id="0" index="13" x="2576" y="96" width="16" height="16" />
			<Object id="0" index="45" x="2528" y="96" width="16" height="16" />
			<Object id="0" index="46" x="2528" y="80" width="16" height="16" />
			<Object id="0" index="45" x="2560" y="96" width="16" height="16" />
			<Object id="0" index="46" x="2560" y="80" width="16" height="16" />
			<Object id="0" index="13" x="2544" y="96" width="16" height="16" />
			<Object id="0" index="13" x="2544" y="80" width="16" height="16" />
			<Object id="0" index="44" x="2512" y="112" width="16" height="16" />
			<Object id="0" index="44" x="2528" y="112" width="16" height="16" />
			<Object id="0" index="44" x="2544" y="112" width="16" height="16" />
			<Object id="0" index="44" x="2560" y="112" width="16" height="16" />
			<Object id="0" index="44" x="2576" y="112" width="16" height="16" />
			<Object id="0" index="13" x="2512" y="128" width="16" height="16" />
			<Object id="0" index="13" x="2512" y="144" width="16" height="16" />
			<Object id="0" index="13" x="2576" y="128" width="16" height="16" />
			<Object id="0" index="13" x="2576" y="144" width="16" height="16" />
			<Object id="0" index="45" x="2544" y="144" width="16" height="16" />
			<Object id="0" index="46" x="2544" y="128" width="16" height="16" />
			<Object id="0" index="13" x="2528" y="144" width="16" height="16" />
			<Object id="0" index="13" x="2528" y="128" width="16" height="16" />
			<Object id="0" index="13" x="2560" y="144" width="16" height="16" />
			<Object id="0" index="13" x="2560" y="128" width="16" height="16" />
			<Object id="0" index="11" x="2512" y="160" width="16" height="16" />
			<Object id="0" index="11" x="2576" y="160" width="16" height="16" />
			<Object id="0" index="44" x="2528" y="160" width="16" height="16" />
			<Object id="0" index="44" x="2544" y="160" width="16" height="16" />
			<Object id="0" index="44" x="2560" y="160" width="16" height="16" />
			<Object id="0" index="661" x="2464" y="112" width="16" height="16" />
			<Object id="0" index="694" x="2464" y="96" width="16" height="16" />
			<Object id="1" index="0" x="2064" y="-32" width="568" height="64" />
		</Node>
	</Quadtree>
</Game>